CHANGES.rst
MANIFEST.in
README.rst
setup.cfg
setup.py
PyLocache.egg-info/PKG-INFO
PyLocache.egg-info/SOURCES.txt
PyLocache.egg-info/dependency_links.txt
PyLocache.egg-info/not-zip-safe
PyLocache.egg-info/top_level.txt
pylocache/__init__.py
pylocache/localcache.py
tests/__init__.py
tests/tests.py