Metadata-Version: 1.1
Name: PyLocache
Version: 0.0.4
Summary: PyLocache is a Python implementation of LRU local cache.
Home-page: https://github.com/psjay/PyLocache
Author: psjay
Author-email: psjay.peng@gmail.com
License: WTFPL
Platform: UNKNOWN
Classifier: Programming Language :: Python
Classifier: Programming Language :: Python :: 2
Classifier: Programming Language :: Python :: 2.7
Classifier: Programming Language :: Python :: 3
Classifier: Programming Language :: Python :: 3.3
Classifier: Operating System :: OS Independent
Classifier: Topic :: Software Development :: Libraries
Classifier: Topic :: Utilities
